sqlang/__init__.py
sqlang/sql.py
tests/__init__.py
tests/test_basic_sql.py
tests/test_basic_sql_expansion.py
tests/test_extension.py
tests/test_iteration_2.py
sqlang-0.2.dist-info/LICENSE
sqlang-0.2.dist-info/METADATA
sqlang-0.2.dist-info/WHEEL
sqlang-0.2.dist-info/top_level.txt
sqlang-0.2.dist-info/RECORD
