Metadata-Version: 2.1
Name: sqlang
Version: 0.2
Summary: Generate SQL programmatically with function calls
Home-page: https://github.com/matthewnicol/sqlang
Author: Matthew Nicol
Author-email: matthew.b.nicol@gmail.com
License: UNKNOWN
Platform: UNKNOWN
Classifier: Programming Language :: Python :: 3
Classifier: License :: OSI Approved :: MIT License
Classifier: Operating System :: OS Independent
Requires-Python: >=3.6
